{
  "_class": "shapePath",
  "booleanOperation": -1,
  "clippingMaskMode": 0,
  "do_objectID": "A0261C09-0262-41D1-B1C0-5009DE815C14",
  "edited": true,
  "exportOptions": {
    "_class": "exportOptions",
    "exportFormats": [
    ],
    "includedLayerIds": [
    ],
    "layerOptions": 0,
    "shouldTrim": false
  },
  "frame": {
    "_class": "rect",
    "constrainProportions": false,
    "height": 25.80645161290323,
    "width": 45.16129032258065,
    "x": 27.41935483870968,
    "y": 70.96774193548387
  },
  "hasClippingMask": false,
  "isClosed": true,
  "isFixedToViewport": false,
  "isFlippedHorizontal": false,
  "isFlippedVertical": false,
  "isLocked": false,
  "isVisible": true,
  "layerListExpandedType": 0,
  "name": "Path",
  "nameIsFixed": false,
  "pointRadiusBehaviour": 1,
  "points": [
    {
      "_class": "curvePoint",
      "cornerRadius": 0,
      "curveFrom": "{1, 0.125}",
      "curveMode": 4,
      "curveTo": "{1, 0.056060789062499783}",
      "hasCurveFrom": false,
      "hasCurveTo": true,
      "point": "{1, 0.125}"
    },
    {
      "_class": "curvePoint",
      "cornerRadius": 0,
      "curveFrom": "{0.8571428571428571, 0.125}",
      "curveMode": 1,
      "curveTo": "{0.8571428571428571, 0.125}",
      "hasCurveFrom": false,
      "hasCurveTo": false,
      "point": "{0.8571428571428571, 0.125}"
    },
    {
      "_class": "curvePoint",
      "cornerRadius": 0,
      "curveFrom": "{0.8571428571428571, 0.25}",
      "curveMode": 1,
      "curveTo": "{0.8571428571428571, 0.25}",
      "hasCurveFrom": false,
      "hasCurveTo": false,
      "point": "{0.8571428571428571, 0.25}"
    },
    {
      "_class": "curvePoint",
      "cornerRadius": 0,
      "curveFrom": "{1, 0.25}",
      "curveMode": 1,
      "curveTo": "{1, 0.25}",
      "hasCurveFrom": false,
      "hasCurveTo": false,
      "point": "{1, 0.25}"
    },
    {
      "_class": "curvePoint",
      "cornerRadius": 0,
      "curveFrom": "{1, 0.75}",
      "curveMode": 1,
      "curveTo": "{1, 0.75}",
      "hasCurveFrom": false,
      "hasCurveTo": false,
      "point": "{1, 0.75}"
    },
    {
      "_class": "curvePoint",
      "cornerRadius": 0,
      "curveFrom": "{0.8571428571428571, 0.75}",
      "curveMode": 1,
      "curveTo": "{0.8571428571428571, 0.75}",
      "hasCurveFrom": false,
      "hasCurveTo": false,
      "point": "{0.8571428571428571, 0.75}"
    },
    {
      "_class": "curvePoint",
      "cornerRadius": 0,
      "curveFrom": "{0.8571428571428571, 0.875}",
      "curveMode": 1,
      "curveTo": "{0.8571428571428571, 0.875}",
      "hasCurveFrom": false,
      "hasCurveTo": false,
      "point": "{0.8571428571428571, 0.875}"
    },
    {
      "_class": "curvePoint",
      "cornerRadius": 0,
      "curveFrom": "{1, 0.94393921093749977}",
      "curveMode": 4,
      "curveTo": "{1, 0.875}",
      "hasCurveFrom": true,
      "hasCurveTo": false,
      "point": "{1, 0.875}"
    },
    {
      "_class": "curvePoint",
      "cornerRadius": 0,
      "curveFrom": "{0.9285714285714286, 1}",
      "curveMode": 4,
      "curveTo": "{0.96796526339285727, 1}",
      "hasCurveFrom": false,
      "hasCurveTo": true,
      "point": "{0.9285714285714286, 1}"
    },
    {
      "_class": "curvePoint",
      "cornerRadius": 0,
      "curveFrom": "{0.032034736607142858, 1}",
      "curveMode": 4,
      "curveTo": "{0.071428571428571425, 1}",
      "hasCurveFrom": true,
      "hasCurveTo": false,
      "point": "{0.071428571428571425, 1}"
    },
    {
      "_class": "curvePoint",
      "cornerRadius": 0,
      "curveFrom": "{0, 0.875}",
      "curveMode": 4,
      "curveTo": "{0, 0.94393921093750022}",
      "hasCurveFrom": false,
      "hasCurveTo": true,
      "point": "{0, 0.875}"
    },
    {
      "_class": "curvePoint",
      "cornerRadius": 0,
      "curveFrom": "{0.14285714285714285, 0.875}",
      "curveMode": 1,
      "curveTo": "{0.14285714285714285, 0.875}",
      "hasCurveFrom": false,
      "hasCurveTo": false,
      "point": "{0.14285714285714285, 0.875}"
    },
    {
      "_class": "curvePoint",
      "cornerRadius": 0,
      "curveFrom": "{0.14285714285714285, 0.75}",
      "curveMode": 1,
      "curveTo": "{0.14285714285714285, 0.75}",
      "hasCurveFrom": false,
      "hasCurveTo": false,
      "point": "{0.14285714285714285, 0.75}"
    },
    {
      "_class": "curvePoint",
      "cornerRadius": 0,
      "curveFrom": "{0, 0.75}",
      "curveMode": 1,
      "curveTo": "{0, 0.75}",
      "hasCurveFrom": false,
      "hasCurveTo": false,
      "point": "{0, 0.75}"
    },
    {
      "_class": "curvePoint",
      "cornerRadius": 0,
      "curveFrom": "{0, 0.25}",
      "curveMode": 1,
      "curveTo": "{0, 0.25}",
      "hasCurveFrom": false,
      "hasCurveTo": false,
      "point": "{0, 0.25}"
    },
    {
      "_class": "curvePoint",
      "cornerRadius": 0,
      "curveFrom": "{0.14285714285714285, 0.25}",
      "curveMode": 1,
      "curveTo": "{0.14285714285714285, 0.25}",
      "hasCurveFrom": false,
      "hasCurveTo": false,
      "point": "{0.14285714285714285, 0.25}"
    },
    {
      "_class": "curvePoint",
      "cornerRadius": 0,
      "curveFrom": "{0.14285714285714285, 0.125}",
      "curveMode": 1,
      "curveTo": "{0.14285714285714285, 0.125}",
      "hasCurveFrom": false,
      "hasCurveTo": false,
      "point": "{0.14285714285714285, 0.125}"
    },
    {
      "_class": "curvePoint",
      "cornerRadius": 0,
      "curveFrom": "{0, 0.056060789062500227}",
      "curveMode": 4,
      "curveTo": "{0, 0.125}",
      "hasCurveFrom": true,
      "hasCurveTo": false,
      "point": "{0, 0.125}"
    },
    {
      "_class": "curvePoint",
      "cornerRadius": 0,
      "curveFrom": "{0.071428571428571425, 0}",
      "curveMode": 4,
      "curveTo": "{0.032034736607142858, 0}",
      "hasCurveFrom": false,
      "hasCurveTo": true,
      "point": "{0.071428571428571425, 0}"
    },
    {
      "_class": "curvePoint",
      "cornerRadius": 0,
      "curveFrom": "{0.96796526339285704, 0}",
      "curveMode": 4,
      "curveTo": "{0.9285714285714286, 0}",
      "hasCurveFrom": true,
      "hasCurveTo": false,
      "point": "{0.9285714285714286, 0}"
    }
  ],
  "resizingConstraint": 63,
  "resizingType": 0,
  "rotation": 0,
  "shouldBreakMaskChain": false,
  "style": {
    "_class": "style",
    "endMarkerType": 0,
    "miterLimit": 10,
    "startMarkerType": 0,
    "windingRule": 1
  }
}