{
  "_class": "group",
  "booleanOperation": -1,
  "clippingMaskMode": 0,
  "do_objectID": "88047EC0-5197-47DF-BB0D-CF284E48456D",
  "exportOptions": {
    "_class": "exportOptions",
    "do_objectID": "BA70146C-E4B9-4A3F-8B05-EC7A8E38EF9F",
    "exportFormats": [
    ],
    "includedLayerIds": [
    ],
    "layerOptions": 0,
    "shouldTrim": false
  },
  "frame": {
    "_class": "rect",
    "constrainProportions": false,
    "do_objectID": "4BE23724-F6A5-435F-AB97-67450B9D89BC",
    "height": 24,
    "width": 180,
    "x": 383,
    "y": 3690
  },
  "hasClickThrough": false,
  "hasClippingMask": false,
  "isFixedToViewport": false,
  "isFlippedHorizontal": false,
  "isFlippedVertical": false,
  "isLocked": false,
  "isVisible": true,
  "layerListExpandedType": 0,
  "layers": [
    {
      "class": "text",
      "id": "B2F46B26-83C0-43EC-B5AF-46E7C54A73A9"
    },
    {
      "class": "text",
      "id": "25E00179-BC0A-4FAD-A869-F7592DC53349"
    }
  ],
  "name": "Group 6 Copy 3",
  "nameIsFixed": false,
  "resizingConstraint": 63,
  "resizingType": 0,
  "rotation": 0,
  "shouldBreakMaskChain": false,
  "style": {
    "_class": "style",
    "do_objectID": "44926448-6213-493E-9604-BEE6016FFEED",
    "endMarkerType": 0,
    "miterLimit": 10,
    "startMarkerType": 0,
    "windingRule": 1
  },
  "userInfo": {
    "com.animaapp.stc-sketch-plugin": {
      "kModelPropertiesKey": {
      }
    }
  }
}