{
  "_class": "group",
  "booleanOperation": -1,
  "clippingMaskMode": 0,
  "do_objectID": "144FA11C-854D-4F88-94EC-2C9B6D382463",
  "exportOptions": {
    "_class": "exportOptions",
    "exportFormats": [
    ],
    "includedLayerIds": [
    ],
    "layerOptions": 0,
    "shouldTrim": false
  },
  "frame": {
    "_class": "rect",
    "constrainProportions": true,
    "height": 101.6129032258065,
    "width": 100,
    "x": 1397,
    "y": 1124
  },
  "hasClickThrough": false,
  "hasClippingMask": false,
  "isFixedToViewport": false,
  "isFlippedHorizontal": false,
  "isFlippedVertical": false,
  "isLocked": false,
  "isVisible": true,
  "layerListExpandedType": 0,
  "layers": [
    {
      "class": "shapeGroup",
      "id": "F28F1A8D-A49D-410C-A666-7B5C8FAE8B7A"
    },
    {
      "class": "shapeGroup",
      "id": "7AA00F1A-6F72-4BC0-B854-9997F6D2912B"
    },
    {
      "class": "shapeGroup",
      "id": "930B1F6A-25B8-498F-A401-364DD7E0E132"
    },
    {
      "class": "shapePath",
      "id": "CFB9373F-429D-48F6-BB89-F9A486546FA7"
    },
    {
      "class": "shapePath",
      "id": "D449C869-E420-49CA-B98B-BF8E1753A5A0"
    },
    {
      "class": "shapePath",
      "id": "D964E446-D066-48A7-9299-3BF0C0CAF5D9"
    },
    {
      "class": "shapePath",
      "id": "90B39AB4-746F-43EA-86DC-C7BCE10045FB"
    },
    {
      "class": "shapePath",
      "id": "2C52A039-EAF1-4F64-94AA-D2B17465EBD1"
    },
    {
      "class": "shapePath",
      "id": "6E1FF35E-0019-41E8-B4A3-F02665BCF841"
    }
  ],
  "name": "maintenance",
  "nameIsFixed": false,
  "resizingConstraint": 63,
  "resizingType": 0,
  "rotation": 0,
  "shouldBreakMaskChain": false,
  "style": {
    "_class": "style",
    "endMarkerType": 0,
    "miterLimit": 10,
    "startMarkerType": 0,
    "windingRule": 1
  },
  "userInfo": {
    "com.animaapp.stc-sketch-plugin": {
      "kModelPropertiesKey": {
        "constraints": {
          "aspectRatio": {
            "constant": 101.6129,
            "enabled": 1,
            "modelID": "constraint_4974ae34-0258-4f4d-883f-f922420a9cbb",
            "model_class": "ADModelConstraint",
            "model_version": 0.1,
            "multiplier": 100
          },
          "automatic": 1,
          "modelID": "viewConstraints_185e15d6-f2cf-4d33-8d3a-f865a2d362a9",
          "model_class": "ADModelViewConstraints",
          "model_version": 0.1,
          "scaleFactor": 1
        }
      }
    }
  }
}